docs/conf.py
postmd/__init__.py
postmd/analysis/__init__.py
postmd/analysis/base.py
postmd/analysis/dielelctric_constant.py
postmd/analysis/diffusion_coefficient.py
postmd/analysis/shear_viscosity.py
postmd/animate/__init__.py
postmd/animate/animate.py
postmd/avechunk/__init__.py
postmd/avechunk/bin1d.py
postmd/avetime/__init__.py
postmd/avetime/avetime.py
postmd/dump/__init__.py
postmd/dump/extract_dump.sh
postmd/log/__init__.py
postmd/log/dir.py
postmd/log/logfile.py
postmd/mplstyles/Readme.md
postmd/mplstyles/notebook.mplstyle
postmd/mplstyles/scatter.mplstyle
postmd/mplstyles/science.mplstyle
postmd/mplstyles/Arial/Arial.mplstyle
postmd/mplstyles/Arial/Arial.pdf
postmd/mplstyles/Arial/Arial.py
postmd/mplstyles/Times/Times.mplstyle
postmd/mplstyles/Times/Times.pdf
postmd/mplstyles/Times/Times.py
postmd/mplstyles/Type42-DejaVu Sans/Type42-DejaVu Sans.mplstyle
postmd/mplstyles/Type42-DejaVu Sans/Type42-DejaVu Sans.py
postmd/mplstyles/Type42-DejaVu Sans/Type42-DejaVu Sans_preview.pdf
postmd/mplstyles/Type42-Times-stix/Type42-Times-stix.mplstyle
postmd/mplstyles/Type42-Times-stix/Type42-Times-stix.py
postmd/mplstyles/Type42-Times-stix/Type42-Times-stix_preview.pdf
postmd/mplstyles/color/bright.mplstyle
postmd/mplstyles/color/high-contrast.mplstyle
postmd/mplstyles/color/high-vis.mplstyle
postmd/mplstyles/color/light.mplstyle
postmd/mplstyles/color/muted.mplstyle
postmd/mplstyles/color/retro.mplstyle
postmd/mplstyles/color/std-colors.mplstyle
postmd/mplstyles/color/vibrant.mplstyle
postmd/mplstyles/color/discrete-rainbow/discrete-rainbow-1.mplstyle
postmd/mplstyles/color/discrete-rainbow/discrete-rainbow-10.mplstyle
postmd/mplstyles/color/discrete-rainbow/discrete-rainbow-11.mplstyle
postmd/mplstyles/color/discrete-rainbow/discrete-rainbow-12.mplstyle
postmd/mplstyles/color/discrete-rainbow/discrete-rainbow-13.mplstyle
postmd/mplstyles/color/discrete-rainbow/discrete-rainbow-14.mplstyle
postmd/mplstyles/color/discrete-rainbow/discrete-rainbow-15.mplstyle
postmd-0.1.2.dist-info/LICENSE
postmd-0.1.2.dist-info/METADATA
postmd-0.1.2.dist-info/WHEEL
postmd-0.1.2.dist-info/entry_points.txt
postmd-0.1.2.dist-info/top_level.txt
postmd-0.1.2.dist-info/RECORD
